gdorker/__init__.py
gdorker/config.example.json
gdorker-1.0.4.dist-info/METADATA
gdorker-1.0.4.dist-info/WHEEL
gdorker-1.0.4.dist-info/entry_points.txt
gdorker-1.0.4.dist-info/RECORD
