Metadata-Version: 2.4
Name: gdorker
Version: 1.0.4
Summary: Script for automation search/dorking with Google and Duckduckgo
Project-URL: Repository, https://github.com/la1n23/gdorker.git
Author-email: La1n Iwakura <la1n23@proton.me>
License-Expression: MIT
Keywords: Duckduckgo,dorking,google,search
Classifier: Development Status :: 4 - Beta
Classifier: Programming Language :: Python :: 3
Requires-Dist: aiohttp
Requires-Dist: beautifulsoup4
Requires-Dist: colorama
Requires-Dist: duckduckgo-search
Requires-Dist: google-api-python-client
